{
  "creds": {
    "noiseKey": {
      "private": {
        "type": "Buffer",
        "data": "ALIbsCOwq25y1V/H6/BMLI93kpOMEXyC+iQ2K81tfkA="
      },
      "public": {
        "type": "Buffer",
        "data": "yTSuL4FtWaRPwYLkX/yl6/9pXvlqyNrn/+bwf3eI0ik="
      }
    },
    "signedIdentityKey": {
      "private": {
        "type": "Buffer",
        "data": "YM1BbBzoWjmaufUN/+X5QkGiKW5Mm9SCqQ/C/4wgikQ="
      },
      "public": {
        "type": "Buffer",
        "data": "/wC64Ivm0M7c1HAnVeD2ZzFHNbGN96yGh5IKrcu3bH4="
      }
    },
    "signedPreKey": {
      "keyPair": {
        "private": {
          "type": "Buffer",
          "data": "uL9qGeqxmXRbdqIp8QkLBqb6qBLFpIPSVEcDDc1KSUo="
        },
        "public": {
          "type": "Buffer",
          "data": "EW+K7iShTXQYapKHyWAx7GrCjDtbTb4J5A5m++/T00I="
        }
      },
      "signature": {
        "type": "Buffer",
        "data": "WyFmPIonj1piRdHGXykdiSjAMIddbMczavmZBaTA2yfrHg74dgIpzS1vZJkFr+vcDtz/baNg8DauqpxpmozshQ=="
      },
      "keyId": 1
    },
    "registrationId": 105,
    "advSecretKey": "p2LLpMOF1Cgma4SPXPumR4WSLei9t+seTo+6OrRlBvA=",
    "processedHistoryMessages": [
      {
        "key": {
          "remoteJid": "62895351467950@s.whatsapp.net",
          "fromMe": true,
          "id": "3EFF894843AED3144ABD83B846FF24A4"
        },
        "messageTimestamp": 1673332942
      },
      {
        "key": {
          "remoteJid": "62895351467950@s.whatsapp.net",
          "fromMe": true,
          "id": "790C54A465D5935C535837B962C1A864"
        },
        "messageTimestamp": 1673332945
      },
      {
        "key": {
          "remoteJid": "62895351467950@s.whatsapp.net",
          "fromMe": true,
          "id": "49A77999457ACA8597B412BDB7BE8C17"
        },
        "messageTimestamp": 1673332946
      }
    ],
    "nextPreKeyId": 31,
    "firstUnuploadedPreKeyId": 31,
    "accountSettings": {
      "unarchiveChats": false
    },
    "account": {
      "details": "CNnT7u4BEMOR9J0GGAE=",
      "accountSignatureKey": "2CvRNi/pvuy+nmQniNLyjAnGYm96b5TGm9NISRQfCW4=",
      "accountSignature": "o7H9Lnj+R5MQUk5g5MaNAvp72saRyQNtgxKxtRw5BK1b7YbctatEkpmf8h7x7fLLK0Beu0ZZ4UdMO4B30qjrAA==",
      "deviceSignature": "tks0WTC5gftRgTfcTU+Tb9u/wXzOX4g1ozWsAv7L5hwpYjcgnRBvq7Ym5PiMlI24bGzg3gvrseAN6FBKgLz6gw=="
    },
    "me": {
      "id": "62895351467950:22@s.whatsapp.net",
      "name": "Dimass"
    },
    "signalIdentities": [
      {
        "identifier": {
          "name": "62895351467950:22@s.whatsapp.net",
          "deviceId": 0
        },
        "identifierKey": {
          "type": "Buffer",
          "data": "Bdgr0TYv6b7svp5kJ4jS8owJxmJvem+UxpvTSEkUHwlu"
        }
      }
    ],
    "platform": "android",
    "lastAccountSyncTimestamp": 1673332935,
    "myAppStateKeyId": "AAAAAHN3"
  },
  "keys": {
    "preKeys": {
      "1": {
        "private": {
          "type": "Buffer",
          "data": "GJZouhRO3NqXsqiv3Cop14z7Rp+XOw7p4Ju+kSB/S0M="
        },
        "public": {
          "type": "Buffer",
          "data": "FneghiY9NMfCUiy6h4ffo2oxbivIDm/m8yFsUxv5jW8="
        }
      },
      "2": {
        "private": {
          "type": "Buffer",
          "data": "ACUha06TrbicVh+BAA7PnipNhsn7NTU1vsiLxRybc3E="
        },
        "public": {
          "type": "Buffer",
          "data": "yjEhY8yz9UcJSi09mH70okxjvYG/Zluiui8ieCsqYzE="
        }
      },
      "3": {
        "private": {
          "type": "Buffer",
          "data": "EDYEK570D+BZiJG7SDnGhOImB4SApIDB3gBGg+ktqG0="
        },
        "public": {
          "type": "Buffer",
          "data": "5BFe6jP4u/lw9jepRcNsaEXjBjP9jgWv0UlJE4f3xRY="
        }
      },
      "4": {
        "private": {
          "type": "Buffer",
          "data": "EFU0HkHdtArYs/NFg0VS9sEsEbWShIrae4soATLQA3I="
        },
        "public": {
          "type": "Buffer",
          "data": "DHHQvvwpT25av7AnteWHjxJFSsPDJEMREilLdkYnlTQ="
        }
      },
      "5": {
        "private": {
          "type": "Buffer",
          "data": "EENjFe7Vt/yECz8QyorriWMvhIg1nfQbgFRQZlx3qHM="
        },
        "public": {
          "type": "Buffer",
          "data": "plnhpIHLj+6+VH1KHY7OGtioubixT3QXOUcKG9FMdjg="
        }
      },
      "6": {
        "private": {
          "type": "Buffer",
          "data": "qDXgybAmWzKp6v/5FZuNPnmDHMv8MoiddjrSKzIN+mg="
        },
        "public": {
          "type": "Buffer",
          "data": "L0wlgYhtlu+495cjUD5oKdfRL5PdKQQuef59HrfsJBQ="
        }
      },
      "7": null,
      "8": {
        "private": {
          "type": "Buffer",
          "data": "8LYnH10tS6rw/DWtXDReAIy6uAVH6TU+damUVz0q2HM="
        },
        "public": {
          "type": "Buffer",
          "data": "bf6CReambATn+mS1WM1yr1OY9F1H5yr5oImEAkCWnA8="
        }
      },
      "9": {
        "private": {
          "type": "Buffer",
          "data": "0CrLwAvVhUl9ff0FzHTkq4b2KRSPtYeGwV2bkcgtekQ="
        },
        "public": {
          "type": "Buffer",
          "data": "pb2SYdXyi12DtOpHyf4tDwgN+Df3CxOb4TqC8mU6gTE="
        }
      },
      "10": {
        "private": {
          "type": "Buffer",
          "data": "0Jc/8bxSJ3S9enEeouNcvUklAXcB0hmrahnZLTQ2oUY="
        },
        "public": {
          "type": "Buffer",
          "data": "FyCGUTSYSXfod/3BT/WFXXxA9Q51r7jQiRhh2i7bMhw="
        }
      },
      "11": {
        "private": {
          "type": "Buffer",
          "data": "MFR8i2scjD1gOBVgh6CkYU6hS8zq6gSY7UTc3mWarEU="
        },
        "public": {
          "type": "Buffer",
          "data": "VFlDKir1r/NoiB8vHeRW8sxVfzDj/tPSQe97b39vQHs="
        }
      },
      "12": {
        "private": {
          "type": "Buffer",
          "data": "gF/4dB4evIyP/69CWrsp4zLjiS7B9554li1WhCW7f30="
        },
        "public": {
          "type": "Buffer",
          "data": "RI/9gwPcnJpeUeoxeXJRhYLCExW8/DVfmaeT5k8lTgs="
        }
      },
      "13": {
        "private": {
          "type": "Buffer",
          "data": "IPyViZ9GlY/Mo+JHV/q8op+d2vftKy+EpICk5rOJ73g="
        },
        "public": {
          "type": "Buffer",
          "data": "l44+pyiHmduEW8AIiwm2LgWTx9lsi0mutIqZRqNEzgw="
        }
      },
      "14": {
        "private": {
          "type": "Buffer",
          "data": "IGiXxX9jyqs/yIP8bHWmE5c/+7sqmqBV4AQDhy5+M2M="
        },
        "public": {
          "type": "Buffer",
          "data": "R/GUv1DimY5ImVimIoMXxzW8PrdkfkWoXtc4tCEv1BA="
        }
      },
      "15": {
        "private": {
          "type": "Buffer",
          "data": "QEkATVKRSTFENKfapRsy+FXnqEFuzxo0lbQfYGpSz04="
        },
        "public": {
          "type": "Buffer",
          "data": "t/pJcj6pABn4cHHnXbSEIJOv38QisLc2Oc9tvZwTjFw="
        }
      },
      "16": {
        "private": {
          "type": "Buffer",
          "data": "+OQ7A1C6xX4VUQeZSd5bbQZL8I14qj0uUnSgsjRVRm8="
        },
        "public": {
          "type": "Buffer",
          "data": "Li/MhVlyOcZzTsyDGQT/dcBLUyfkZ+a3A7NMs0EHA24="
        }
      },
      "17": {
        "private": {
          "type": "Buffer",
          "data": "8HfjTKt/h+ESY7icfO4DvjLqufl6YrhTWzA+4y+aoWg="
        },
        "public": {
          "type": "Buffer",
          "data": "YT9Dluy4EifM00ov3xTPTJewIJTN+qEgoWDrGXpxVRU="
        }
      },
      "18": {
        "private": {
          "type": "Buffer",
          "data": "qGcJL/++Bz9OmPmmWLxzscSXiRfW/VUekfeMuMJdFGk="
        },
        "public": {
          "type": "Buffer",
          "data": "suOr1u3iW5YPfVCNskwCs9wZDjTllYEb+uMRHl08xxc="
        }
      },
      "19": {
        "private": {
          "type": "Buffer",
          "data": "EC4Ae3RwLZcuICAzHPD0TpzTH8CX9SUfRnNDkIBeI0E="
        },
        "public": {
          "type": "Buffer",
          "data": "71mZlXobbadUxafpsZweyW0myXnVRiHTorM5AZvgNT0="
        }
      },
      "20": {
        "private": {
          "type": "Buffer",
          "data": "mEBeOLcRZihp40UGf31hRzAyZnvWJuic2mWAa25PeG4="
        },
        "public": {
          "type": "Buffer",
          "data": "nCZmdy41OS73aT371y5JiOgn/HLEZXeSZovAb6z2RzQ="
        }
      },
      "21": {
        "private": {
          "type": "Buffer",
          "data": "uNZX6snR5odOuSWpMmwLPyUYmAZ2MV0E9ZJlAxizqHM="
        },
        "public": {
          "type": "Buffer",
          "data": "F3uQZo+nhfTfWFBrkNCBndlku4DC2eWcUkkiEmpJYC0="
        }
      },
      "22": {
        "private": {
          "type": "Buffer",
          "data": "UPLgUNZWUuQ9D9zf+X5zupM3YI4fN0dhR9/D/rTfvlg="
        },
        "public": {
          "type": "Buffer",
          "data": "Ltfd+tUCC5UgfyQ24ahhdtpSwL+LRQ1EWtZ7Tf0izgs="
        }
      },
      "23": {
        "private": {
          "type": "Buffer",
          "data": "UCLZai6PhSwqgQdFaLFGFKd/BfxQUs0myx9Kv/XVPXE="
        },
        "public": {
          "type": "Buffer",
          "data": "CAY5dMpdb/fzhlf9R2aLXaJ60t6IpuxdX2mRjGZXlTo="
        }
      },
      "24": {
        "private": {
          "type": "Buffer",
          "data": "2MCpzJSK1x2hQTHY05QjmgxSz/SvOIsL0QJHq8Y1cHo="
        },
        "public": {
          "type": "Buffer",
          "data": "Gag1Bm6TPGaI6st1qVocP5VN5x691Mfnl5thp3hmViI="
        }
      },
      "25": {
        "private": {
          "type": "Buffer",
          "data": "0PMhbek6qWTnmpnm4J+aOGDiCqlaHx1NwA55P3a0NnA="
        },
        "public": {
          "type": "Buffer",
          "data": "tEAUFDQ4I3xFIs+kZmH8vn/6jo4X7pCMI5P9MoiXHig="
        }
      },
      "26": {
        "private": {
          "type": "Buffer",
          "data": "QDpgqR3ZTtqaTajsf7yilw697vi7UgnmQACFH1WSuG4="
        },
        "public": {
          "type": "Buffer",
          "data": "Gip+s6nHO+grrOKJk5p/D9HNTE8AXb2XNb3gvwfNOHg="
        }
      },
      "27": {
        "private": {
          "type": "Buffer",
          "data": "4DJuOeoi7y1G7q8inAfkuJPdceJKOG02wFNHxwp33HQ="
        },
        "public": {
          "type": "Buffer",
          "data": "c/LfRjd/6Q1B1qDkq2lZbILhcWSoAeYK9YXqtJZakBo="
        }
      },
      "28": {
        "private": {
          "type": "Buffer",
          "data": "YMAf0qr6PQ8VbuEfVisb4aLPW0vmzAXIHbZEDzEzZ1Y="
        },
        "public": {
          "type": "Buffer",
          "data": "A9JhycwmCWz3JaMUHZw2uyGndLAF8hVT++tU871c1xw="
        }
      },
      "29": {
        "private": {
          "type": "Buffer",
          "data": "WM/HqHmK7VALRqfQ6HxKUb33O/WJ6ruUtNCY1Oo58X8="
        },
        "public": {
          "type": "Buffer",
          "data": "8cw79R2mpOfhM1gn5dRrtHX7RuwIeQzPZlnFBRgFN2g="
        }
      },
      "30": {
        "private": {
          "type": "Buffer",
          "data": "uOXeMwXv1gW0Dy4yBkNTPn2bemOm2OyTFS6CHxCsJFg="
        },
        "public": {
          "type": "Buffer",
          "data": "r340BnX44TN0jJAy/2hnkB0Bgl6MPTu8osex4LfziwE="
        }
      }
    },
    "sessions": {
      "62895351467950.0": {
        "_sessions": {
          "BUymtO0n5mz+yrp+L6YPkM8XJCwsQpok6y+/ZRf1sAZj": {
            "registrationId": 1655274753,
            "currentRatchet": {
              "ephemeralKeyPair": {
                "pubKey": "BSXqfl+7lyyK+PgjQHIu/9uc7l2FJB0L/h5kIVLB60oe",
                "privKey": "oOwfoawnmUJCR3IfgBO7bq3paT1UcZc9D5OxA8X5vVk="
              },
              "lastRemoteEphemeralKey": "BdAfgBrp3fRjEFjGrQnSdhpz4q/Y3Y8pluu8FudsqPUW",
              "previousCounter": 3,
              "rootKey": "tJZDmm9kFgj5Gyaiq+7D9mdM+FZ4ft+dMQuMWQCQEno="
            },
            "indexInfo": {
              "baseKey": "BUymtO0n5mz+yrp+L6YPkM8XJCwsQpok6y+/ZRf1sAZj",
              "baseKeyType": 2,
              "closed": -1,
              "used": 1673332957779,
              "created": 1673332941233,
              "remoteIdentityKey": "Bdgr0TYv6b7svp5kJ4jS8owJxmJvem+UxpvTSEkUHwlu"
            },
            "_chains": {
              "BfogcaR89xsNkYaPfLU7aXespwpenpMA4ZbNCBj2hMFS": {
                "chainKey": {
                  "counter": 3
                },
                "chainType": 2,
                "messageKeys": {}
              },
              "BdhCZLIfoUlmacGKOQrnO+zHQJO8mnUcz2ifgK52FkxU": {
                "chainKey": {
                  "counter": 3
                },
                "chainType": 2,
                "messageKeys": {}
              },
              "BdAfgBrp3fRjEFjGrQnSdhpz4q/Y3Y8pluu8FudsqPUW": {
                "chainKey": {
                  "counter": 0,
                  "key": "iNl8sv2yugZ5/SFje1xK5cIW1AY1OSpoke3m6SrvxRw="
                },
                "chainType": 2,
                "messageKeys": {}
              },
              "BSXqfl+7lyyK+PgjQHIu/9uc7l2FJB0L/h5kIVLB60oe": {
                "chainKey": {
                  "counter": -1,
                  "key": "7y6jRNtYRbedOVMLbkO+NswmiG7VuvXx4WzRY2dvuJg="
                },
                "chainType": 1,
                "messageKeys": {}
              }
            }
          }
        },
        "version": "v1"
      },
      "77759599716.0": {
        "_sessions": {
          "Bcg/eJix7Moud/ZNM5A+XrM5SoMB1TgihCy0PhbsQSMK": {
            "registrationId": 1141067035,
            "currentRatchet": {
              "ephemeralKeyPair": {
                "pubKey": "BcOhqtfhhl8Ai6laRPo80mrRFJTTre6bfnafgods8fcS",
                "privKey": "eKkN/FFq241ygIopmK0lUUks7ixHSGSGrLTi2ptWxXI="
              },
              "lastRemoteEphemeralKey": "BRB69Uo7kRQGjspnRvMPbPnTQltS1ZhZgn/+GOotAFF/",
              "previousCounter": 0,
              "rootKey": "wrpk6GhuQNygpxoucRnK4xzxBUDBki8kiw3Laxz6fjI="
            },
            "indexInfo": {
              "baseKey": "Bcg/eJix7Moud/ZNM5A+XrM5SoMB1TgihCy0PhbsQSMK",
              "baseKeyType": 1,
              "closed": 1673332942297,
              "used": 1673332942224,
              "created": 1673332942224,
              "remoteIdentityKey": "BWWCRKNlgci3kZ0xC8Nuzcx3ll8Mm9lEZDRZjHpfgr5u"
            },
            "_chains": {
              "BcOhqtfhhl8Ai6laRPo80mrRFJTTre6bfnafgods8fcS": {
                "chainKey": {
                  "counter": 0,
                  "key": "yD2B++B57v5EmNUV07QTibi4/DndDOyx2zYqN/wmEhM="
                },
                "chainType": 1,
                "messageKeys": {}
              }
            },
            "pendingPreKey": {
              "signedKeyId": 2,
              "baseKey": "Bcg/eJix7Moud/ZNM5A+XrM5SoMB1TgihCy0PhbsQSMK"
            }
          },
          "BcLM049yGzWBFYOdYF0C5QDqxqtqx++VA3T45qfsK+Zc": {
            "registrationId": 1141067035,
            "currentRatchet": {
              "ephemeralKeyPair": {
                "pubKey": "BWEHdmKEVRTBIAkiEFaXCB7aTom9jKSyp374/hPoZTlF",
                "privKey": "GJMguTY2R3QRe4Oy1yL6/+PfmByEjJOT8ZKdPjGw9GI="
              },
              "lastRemoteEphemeralKey": "BRB69Uo7kRQGjspnRvMPbPnTQltS1ZhZgn/+GOotAFF/",
              "previousCounter": 0,
              "rootKey": "PtFqNRpZImDKCEIK8VK+0ZfovyspHuCjH0+2f/dHdtg="
            },
            "indexInfo": {
              "baseKey": "BcLM049yGzWBFYOdYF0C5QDqxqtqx++VA3T45qfsK+Zc",
              "baseKeyType": 1,
              "closed": -1,
              "used": 1673332942285,
              "created": 1673332942285,
              "remoteIdentityKey": "BWWCRKNlgci3kZ0xC8Nuzcx3ll8Mm9lEZDRZjHpfgr5u"
            },
            "_chains": {
              "BWEHdmKEVRTBIAkiEFaXCB7aTom9jKSyp374/hPoZTlF": {
                "chainKey": {
                  "counter": 6,
                  "key": "jPNKUQ3SrikonnTJr7Y+20xObsmwerMjmiNL3RyBIqY="
                },
                "chainType": 1,
                "messageKeys": {}
              }
            },
            "pendingPreKey": {
              "signedKeyId": 2,
              "baseKey": "BcLM049yGzWBFYOdYF0C5QDqxqtqx++VA3T45qfsK+Zc"
            }
          }
        },
        "version": "v1"
      }
    },
    "appStateSyncKeys": {
      "AAAAAHN2": {
        "keyData": "iwYszw2/uBdcJSZlYEGVhnURTxDgurJCLwxZg/P64Qg=",
        "fingerprint": {
          "rawId": 500935128,
          "currentIndex": 1,
          "deviceIndexes": [
            0,
            1
          ]
        },
        "timestamp": "1673332547902"
      },
      "AAAAAHN3": {
        "keyData": "xWRHRSpxPhdLKcNSM94wgfsGjrLAb9BjoFnTp66KqLc=",
        "fingerprint": {
          "rawId": 500935128,
          "currentIndex": 1,
          "deviceIndexes": [
            0
          ]
        },
        "timestamp": "1673332638443"
      }
    }
  }
}